torch_linode/__init__.py
torch_linode/butcher.py
torch_linode/dense_output.py
torch_linode/quadrature.py
torch_linode/solvers.py
torch_linode/stepper.py
torch_linode/utils.py
torch_linode-0.3.0.dist-info/LICENSE
torch_linode-0.3.0.dist-info/METADATA
torch_linode-0.3.0.dist-info/WHEEL
torch_linode-0.3.0.dist-info/top_level.txt
torch_linode-0.3.0.dist-info/RECORD
