Metadata-Version: 2.1
Name: torch-linode
Version: 0.3.0
Summary: A PyTorch-based library for solving homogeneous and non-homogeneous linear ODEs using Magnus-type integrators.
Author-email: Wu-Chenyang <wucy@lamda.nju.edu.cn>
Project-URL: Homepage, https://github.com/Wu-Chenyang/torch_linode
Project-URL: Bug Tracker, https://github.com/Wu-Chenyang/torch_linode/issues
Classifier: Programming Language :: Python :: 3
Classifier: License :: OSI Approved :: MIT License
Classifier: Operating System :: OS Independent
Classifier: Intended Audience :: Science/Research
Classifier: Topic :: Scientific/Engineering :: Physics
Classifier: Topic :: Scientific/Engineering :: Mathematics
Requires-Python: >=3.8
License-File: LICENSE
Requires-Dist: torch >=1.10
Requires-Dist: numpy
Requires-Dist: scipy
Provides-Extra: dev
Requires-Dist: pytest ; extra == 'dev'
Requires-Dist: matplotlib ; extra == 'dev'
